greenlab/__init__.py
greenlab/conv2d_pca.py
greenlab/dft.py
greenlab/example.py
greenlab/extract_patches.py
greenlab/pixelhop.py
greenlab/resize.py
greenlab-0.0.3.dist-info/LICENSE
greenlab-0.0.3.dist-info/METADATA
greenlab-0.0.3.dist-info/WHEEL
greenlab-0.0.3.dist-info/top_level.txt
greenlab-0.0.3.dist-info/RECORD
