Metadata-Version: 2.1
Name: greenlab
Version: 0.0.3
Summary: Green Learning Library
Author-email: Hong-Shuo Chen <hongshuo@usc.edu>
Project-URL: Homepage, https://github.com/hongshuochen/greenlab
Project-URL: Bug Tracker, https://github.com/hongshuochen/greenlab/issues
Classifier: Programming Language :: Python :: 3
Classifier: License :: OSI Approved :: MIT License
Classifier: Operating System :: OS Independent
Requires-Python: >=3.7
License-File: LICENSE
